<?xml version="1.0" encoding="utf-8"?>
<playlist listTitle="">
	<mp3file title="» Tipo di lavoro «"></mp3file>
	<mp3file title="Hai una canzone preferita che tratta di un problema sociale, ambientale ecc? Di cosa parla?">../media/audio/a5_a5_01.mp3</mp3file>
	<mp3file title="Secondo te, il testo di una canzone influisce sui giovani?">../media/audio/a5_a5_02.mp3</mp3file>
	<mp3file title="I giovani ascoltano le parole della canzone o seguono piuttosto il ritmo della musica? ">../media/audio/a5_a5_03.mp3</mp3file>
	<mp3file title="Secondo te, la musica è un modo efficace per comunicare ai giovani?">../media/audio/a5_a5_04.mp3</mp3file>
	<mp3file title="Sei stato ad un concerto?">../media/audio/a5_a5_05.mp3</mp3file>
	<mp3file title="Ti piacerebbe andare ad un concerto di benificenza? Perché?">../media/audio/a5_a5_06.mp3</mp3file>
	<mp3file title="Chi è il tuo cantante preferito o la tua band preferita?">../media/audio/a5_a5_07.mp3</mp3file>
		<mp3file title=""></mp3file>
	<mp3file title="» Sensibilizzazione al mondo «"></mp3file>
	<mp3file title="Quali problemi mondiali ti preoccupano?">../media/audio/a5_a5_08.mp3</mp3file>
	<mp3file title="C’è qualche iniziativa nella tua scuola che riguarda una tematica sociale, ambientale o umanitaria?">../media/audio/a5_a5_09.mp3</mp3file>
	<mp3file title="Quale iniziativa nella tua città aiuta a proteggere l’ambiente?">../media/audio/a5_a5_10.mp3</mp3file>
	<mp3file title="Il tuo gruppo d’amici è interessato ai problemi mondiali?">../media/audio/a5_a5_11.mp3</mp3file>
	<mp3file title="I giovani sono menefreghisti riguardo ai problemi mondiali?">../media/audio/a5_a5_12.mp3</mp3file>
	<mp3file title="I giovani in che modo possono aiutare la salvaguardia dell’ambiente?">../media/audio/a5_a5_13.mp3</mp3file>
	<mp3file title="Quando pensi al futuro del mondo cosa ti preoccupa?">../media/audio/a5_a5_14.mp3</mp3file>
	<mp3file title="Ti piacerebbe fare una esperienza di volontariato in un paese sottosviluppato?">../media/audio/a5_a5_15.mp3</mp3file>
</playlist>